<annotation>
	<folder>res</folder>
	<filename>1643469012.0966969.jpg</filename>
	<path>D:\Edu\KozPrjct\res\1643469012.0966969.jpg</path>
	<source>
		<database>Unknown</database>
	</source>
	<size>
		<width>1920</width>
		<height>1080</height>
		<depth>3</depth>
	</size>
	<segmented>0</segmented>
	<object>
		<name>walker</name>
		<pose>Unspecified</pose>
		<truncated>0</truncated>
		<difficult>0</difficult>
		<bndbox>
			<xmin>262</xmin>
			<ymin>525</ymin>
			<xmax>275</xmax>
			<ymax>553</ymax>
		</bndbox>
	</object>
	<object>
		<name>walker</name>
		<pose>Unspecified</pose>
		<truncated>0</truncated>
		<difficult>0</difficult>
		<bndbox>
			<xmin>379</xmin>
			<ymin>492</ymin>
			<xmax>383</xmax>
			<ymax>515</ymax>
		</bndbox>
	</object>
	<object>
		<name>walker</name>
		<pose>Unspecified</pose>
		<truncated>0</truncated>
		<difficult>0</difficult>
		<bndbox>
			<xmin>303</xmin>
			<ymin>472</ymin>
			<xmax>308</xmax>
			<ymax>485</ymax>
		</bndbox>
	</object>
	<object>
		<name>walker</name>
		<pose>Unspecified</pose>
		<truncated>0</truncated>
		<difficult>0</difficult>
		<bndbox>
			<xmin>309</xmin>
			<ymin>464</ymin>
			<xmax>316</xmax>
			<ymax>483</ymax>
		</bndbox>
	</object>
	<object>
		<name>walker</name>
		<pose>Unspecified</pose>
		<truncated>0</truncated>
		<difficult>0</difficult>
		<bndbox>
			<xmin>385</xmin>
			<ymin>493</ymin>
			<xmax>391</xmax>
			<ymax>511</ymax>
		</bndbox>
	</object>
	<object>
		<name>walker</name>
		<pose>Unspecified</pose>
		<truncated>0</truncated>
		<difficult>0</difficult>
		<bndbox>
			<xmin>382</xmin>
			<ymin>485</ymin>
			<xmax>392</xmax>
			<ymax>508</ymax>
		</bndbox>
	</object>
	<object>
		<name>car</name>
		<pose>Unspecified</pose>
		<truncated>0</truncated>
		<difficult>0</difficult>
		<bndbox>
			<xmin>210</xmin>
			<ymin>494</ymin>
			<xmax>249</xmax>
			<ymax>514</ymax>
		</bndbox>
	</object>
	<object>
		<name>car</name>
		<pose>Unspecified</pose>
		<truncated>0</truncated>
		<difficult>0</difficult>
		<bndbox>
			<xmin>89</xmin>
			<ymin>482</ymin>
			<xmax>119</xmax>
			<ymax>500</ymax>
		</bndbox>
	</object>
	<object>
		<name>bus</name>
		<pose>Unspecified</pose>
		<truncated>0</truncated>
		<difficult>0</difficult>
		<bndbox>
			<xmin>181</xmin>
			<ymin>459</ymin>
			<xmax>255</xmax>
			<ymax>498</ymax>
		</bndbox>
	</object>
	<object>
		<name>walker</name>
		<pose>Unspecified</pose>
		<truncated>0</truncated>
		<difficult>0</difficult>
		<bndbox>
			<xmin>1250</xmin>
			<ymin>515</ymin>
			<xmax>1267</xmax>
			<ymax>542</ymax>
		</bndbox>
	</object>
	<object>
		<name>walker</name>
		<pose>Unspecified</pose>
		<truncated>0</truncated>
		<difficult>0</difficult>
		<bndbox>
			<xmin>1214</xmin>
			<ymin>500</ymin>
			<xmax>1226</xmax>
			<ymax>524</ymax>
		</bndbox>
	</object>
	<object>
		<name>walker</name>
		<pose>Unspecified</pose>
		<truncated>0</truncated>
		<difficult>0</difficult>
		<bndbox>
			<xmin>1026</xmin>
			<ymin>475</ymin>
			<xmax>1035</xmax>
			<ymax>500</ymax>
		</bndbox>
	</object>
	<object>
		<name>walker</name>
		<pose>Unspecified</pose>
		<truncated>0</truncated>
		<difficult>0</difficult>
		<bndbox>
			<xmin>1033</xmin>
			<ymin>475</ymin>
			<xmax>1044</xmax>
			<ymax>500</ymax>
		</bndbox>
	</object>
	<object>
		<name>walker</name>
		<pose>Unspecified</pose>
		<truncated>0</truncated>
		<difficult>0</difficult>
		<bndbox>
			<xmin>928</xmin>
			<ymin>440</ymin>
			<xmax>935</xmax>
			<ymax>460</ymax>
		</bndbox>
	</object>
	<object>
		<name>walker</name>
		<pose>Unspecified</pose>
		<truncated>0</truncated>
		<difficult>0</difficult>
		<bndbox>
			<xmin>1281</xmin>
			<ymin>522</ymin>
			<xmax>1290</xmax>
			<ymax>548</ymax>
		</bndbox>
	</object>
	<object>
		<name>walker</name>
		<pose>Unspecified</pose>
		<truncated>0</truncated>
		<difficult>0</difficult>
		<bndbox>
			<xmin>1337</xmin>
			<ymin>531</ymin>
			<xmax>1345</xmax>
			<ymax>561</ymax>
		</bndbox>
	</object>
	<object>
		<name>walker</name>
		<pose>Unspecified</pose>
		<truncated>0</truncated>
		<difficult>0</difficult>
		<bndbox>
			<xmin>1365</xmin>
			<ymin>540</ymin>
			<xmax>1377</xmax>
			<ymax>569</ymax>
		</bndbox>
	</object>
	<object>
		<name>walker</name>
		<pose>Unspecified</pose>
		<truncated>0</truncated>
		<difficult>0</difficult>
		<bndbox>
			<xmin>1400</xmin>
			<ymin>534</ymin>
			<xmax>1411</xmax>
			<ymax>564</ymax>
		</bndbox>
	</object>
	<object>
		<name>walker</name>
		<pose>Unspecified</pose>
		<truncated>0</truncated>
		<difficult>0</difficult>
		<bndbox>
			<xmin>1352</xmin>
			<ymin>530</ymin>
			<xmax>1363</xmax>
			<ymax>558</ymax>
		</bndbox>
	</object>
	<object>
		<name>car</name>
		<pose>Unspecified</pose>
		<truncated>0</truncated>
		<difficult>0</difficult>
		<bndbox>
			<xmin>1043</xmin>
			<ymin>454</ymin>
			<xmax>1086</xmax>
			<ymax>477</ymax>
		</bndbox>
	</object>
	<object>
		<name>car</name>
		<pose>Unspecified</pose>
		<truncated>0</truncated>
		<difficult>0</difficult>
		<bndbox>
			<xmin>1075</xmin>
			<ymin>458</ymin>
			<xmax>1116</xmax>
			<ymax>482</ymax>
		</bndbox>
	</object>
	<object>
		<name>car</name>
		<pose>Unspecified</pose>
		<truncated>0</truncated>
		<difficult>0</difficult>
		<bndbox>
			<xmin>1113</xmin>
			<ymin>463</ymin>
			<xmax>1155</xmax>
			<ymax>486</ymax>
		</bndbox>
	</object>
	<object>
		<name>car</name>
		<pose>Unspecified</pose>
		<truncated>0</truncated>
		<difficult>0</difficult>
		<bndbox>
			<xmin>1156</xmin>
			<ymin>470</ymin>
			<xmax>1196</xmax>
			<ymax>492</ymax>
		</bndbox>
	</object>
	<object>
		<name>car</name>
		<pose>Unspecified</pose>
		<truncated>0</truncated>
		<difficult>0</difficult>
		<bndbox>
			<xmin>1194</xmin>
			<ymin>473</ymin>
			<xmax>1234</xmax>
			<ymax>495</ymax>
		</bndbox>
	</object>
	<object>
		<name>car</name>
		<pose>Unspecified</pose>
		<truncated>0</truncated>
		<difficult>0</difficult>
		<bndbox>
			<xmin>1233</xmin>
			<ymin>464</ymin>
			<xmax>1268</xmax>
			<ymax>487</ymax>
		</bndbox>
	</object>
	<object>
		<name>car</name>
		<pose>Unspecified</pose>
		<truncated>0</truncated>
		<difficult>0</difficult>
		<bndbox>
			<xmin>1267</xmin>
			<ymin>458</ymin>
			<xmax>1300</xmax>
			<ymax>477</ymax>
		</bndbox>
	</object>
	<object>
		<name>car</name>
		<pose>Unspecified</pose>
		<truncated>0</truncated>
		<difficult>0</difficult>
		<bndbox>
			<xmin>1294</xmin>
			<ymin>448</ymin>
			<xmax>1326</xmax>
			<ymax>470</ymax>
		</bndbox>
	</object>
	<object>
		<name>car</name>
		<pose>Unspecified</pose>
		<truncated>0</truncated>
		<difficult>0</difficult>
		<bndbox>
			<xmin>1277</xmin>
			<ymin>444</ymin>
			<xmax>1308</xmax>
			<ymax>463</ymax>
		</bndbox>
	</object>
	<object>
		<name>car</name>
		<pose>Unspecified</pose>
		<truncated>0</truncated>
		<difficult>0</difficult>
		<bndbox>
			<xmin>1242</xmin>
			<ymin>451</ymin>
			<xmax>1277</xmax>
			<ymax>473</ymax>
		</bndbox>
	</object>
	<object>
		<name>car</name>
		<pose>Unspecified</pose>
		<truncated>0</truncated>
		<difficult>0</difficult>
		<bndbox>
			<xmin>1206</xmin>
			<ymin>458</ymin>
			<xmax>1243</xmax>
			<ymax>476</ymax>
		</bndbox>
	</object>
	<object>
		<name>minibus</name>
		<pose>Unspecified</pose>
		<truncated>0</truncated>
		<difficult>0</difficult>
		<bndbox>
			<xmin>1164</xmin>
			<ymin>447</ymin>
			<xmax>1209</xmax>
			<ymax>475</ymax>
		</bndbox>
	</object>
	<object>
		<name>car</name>
		<pose>Unspecified</pose>
		<truncated>0</truncated>
		<difficult>0</difficult>
		<bndbox>
			<xmin>1103</xmin>
			<ymin>521</ymin>
			<xmax>1160</xmax>
			<ymax>551</ymax>
		</bndbox>
	</object>
	<object>
		<name>car</name>
		<pose>Unspecified</pose>
		<truncated>0</truncated>
		<difficult>0</difficult>
		<bndbox>
			<xmin>1188</xmin>
			<ymin>521</ymin>
			<xmax>1228</xmax>
			<ymax>547</ymax>
		</bndbox>
	</object>
</annotation>
