<annotation>
	<folder>Максимук</folder>
	<filename>1643446394.9668555.jpg</filename>
	<path>C:\Users\Gleb\Desktop\Copy\Максимук\1643446394.9668555.jpg</path>
	<source>
		<database>Unknown</database>
	</source>
	<size>
		<width>1920</width>
		<height>1080</height>
		<depth>3</depth>
	</size>
	<segmented>0</segmented>
	<object>
		<name>walker</name>
		<pose>Unspecified</pose>
		<truncated>0</truncated>
		<difficult>0</difficult>
		<bndbox>
			<xmin>210</xmin>
			<ymin>529</ymin>
			<xmax>229</xmax>
			<ymax>562</ymax>
		</bndbox>
	</object>
	<object>
		<name>walker</name>
		<pose>Unspecified</pose>
		<truncated>0</truncated>
		<difficult>0</difficult>
		<bndbox>
			<xmin>223</xmin>
			<ymin>531</ymin>
			<xmax>245</xmax>
			<ymax>573</ymax>
		</bndbox>
	</object>
	<object>
		<name>walker</name>
		<pose>Unspecified</pose>
		<truncated>0</truncated>
		<difficult>0</difficult>
		<bndbox>
			<xmin>668</xmin>
			<ymin>475</ymin>
			<xmax>683</xmax>
			<ymax>495</ymax>
		</bndbox>
	</object>
	<object>
		<name>walker</name>
		<pose>Unspecified</pose>
		<truncated>0</truncated>
		<difficult>0</difficult>
		<bndbox>
			<xmin>1565</xmin>
			<ymin>610</ymin>
			<xmax>1578</xmax>
			<ymax>638</ymax>
		</bndbox>
	</object>
	<object>
		<name>walker</name>
		<pose>Unspecified</pose>
		<truncated>0</truncated>
		<difficult>0</difficult>
		<bndbox>
			<xmin>1545</xmin>
			<ymin>588</ymin>
			<xmax>1561</xmax>
			<ymax>622</ymax>
		</bndbox>
	</object>
	<object>
		<name>walker</name>
		<pose>Unspecified</pose>
		<truncated>0</truncated>
		<difficult>0</difficult>
		<bndbox>
			<xmin>1585</xmin>
			<ymin>523</ymin>
			<xmax>1605</xmax>
			<ymax>551</ymax>
		</bndbox>
	</object>
	<object>
		<name>car</name>
		<pose>Unspecified</pose>
		<truncated>0</truncated>
		<difficult>0</difficult>
		<bndbox>
			<xmin>675</xmin>
			<ymin>519</ymin>
			<xmax>752</xmax>
			<ymax>552</ymax>
		</bndbox>
	</object>
	<object>
		<name>car</name>
		<pose>Unspecified</pose>
		<truncated>0</truncated>
		<difficult>0</difficult>
		<bndbox>
			<xmin>855</xmin>
			<ymin>486</ymin>
			<xmax>916</xmax>
			<ymax>529</ymax>
		</bndbox>
	</object>
	<object>
		<name>car</name>
		<pose>Unspecified</pose>
		<truncated>0</truncated>
		<difficult>0</difficult>
		<bndbox>
			<xmin>956</xmin>
			<ymin>508</ymin>
			<xmax>1032</xmax>
			<ymax>536</ymax>
		</bndbox>
	</object>
	<object>
		<name>car</name>
		<pose>Unspecified</pose>
		<truncated>0</truncated>
		<difficult>0</difficult>
		<bndbox>
			<xmin>1071</xmin>
			<ymin>496</ymin>
			<xmax>1113</xmax>
			<ymax>539</ymax>
		</bndbox>
	</object>
	<object>
		<name>car</name>
		<pose>Unspecified</pose>
		<truncated>0</truncated>
		<difficult>0</difficult>
		<bndbox>
			<xmin>972</xmin>
			<ymin>488</ymin>
			<xmax>1041</xmax>
			<ymax>519</ymax>
		</bndbox>
	</object>
	<object>
		<name>car</name>
		<pose>Unspecified</pose>
		<truncated>0</truncated>
		<difficult>0</difficult>
		<bndbox>
			<xmin>996</xmin>
			<ymin>462</ymin>
			<xmax>1041</xmax>
			<ymax>486</ymax>
		</bndbox>
	</object>
	<object>
		<name>car</name>
		<pose>Unspecified</pose>
		<truncated>0</truncated>
		<difficult>0</difficult>
		<bndbox>
			<xmin>1104</xmin>
			<ymin>452</ymin>
			<xmax>1148</xmax>
			<ymax>489</ymax>
		</bndbox>
	</object>
	<object>
		<name>car</name>
		<pose>Unspecified</pose>
		<truncated>0</truncated>
		<difficult>0</difficult>
		<bndbox>
			<xmin>1146</xmin>
			<ymin>464</ymin>
			<xmax>1195</xmax>
			<ymax>496</ymax>
		</bndbox>
	</object>
	<object>
		<name>car</name>
		<pose>Unspecified</pose>
		<truncated>0</truncated>
		<difficult>0</difficult>
		<bndbox>
			<xmin>1165</xmin>
			<ymin>478</ymin>
			<xmax>1210</xmax>
			<ymax>513</ymax>
		</bndbox>
	</object>
	<object>
		<name>car</name>
		<pose>Unspecified</pose>
		<truncated>0</truncated>
		<difficult>0</difficult>
		<bndbox>
			<xmin>1164</xmin>
			<ymin>450</ymin>
			<xmax>1206</xmax>
			<ymax>476</ymax>
		</bndbox>
	</object>
	<object>
		<name>car</name>
		<pose>Unspecified</pose>
		<truncated>0</truncated>
		<difficult>0</difficult>
		<bndbox>
			<xmin>1211</xmin>
			<ymin>438</ymin>
			<xmax>1250</xmax>
			<ymax>466</ymax>
		</bndbox>
	</object>
	<object>
		<name>car</name>
		<pose>Unspecified</pose>
		<truncated>0</truncated>
		<difficult>0</difficult>
		<bndbox>
			<xmin>1216</xmin>
			<ymin>451</ymin>
			<xmax>1258</xmax>
			<ymax>481</ymax>
		</bndbox>
	</object>
	<object>
		<name>car</name>
		<pose>Unspecified</pose>
		<truncated>0</truncated>
		<difficult>0</difficult>
		<bndbox>
			<xmin>1252</xmin>
			<ymin>455</ymin>
			<xmax>1291</xmax>
			<ymax>485</ymax>
		</bndbox>
	</object>
	<object>
		<name>car</name>
		<pose>Unspecified</pose>
		<truncated>0</truncated>
		<difficult>0</difficult>
		<bndbox>
			<xmin>1271</xmin>
			<ymin>568</ymin>
			<xmax>1328</xmax>
			<ymax>611</ymax>
		</bndbox>
	</object>
</annotation>
